stratovolquant/__init__.py
stratovolquant/version.py
stratovolquant/mongo/__init__.py
stratovolquant/mongo/collection_manager.py
stratovolquant/mongo/create_ref.py
stratovolquant/mongo/database_connection.py
stratovolquant/mongo/referential_instance.py
stratovolquant/mongo/static_data.py
stratovolquant/mongo/symbols_to_arctic.py
stratovolquant/mongo/update_referential.py
stratovolquant/technical/__init__.py
stratovolquant/technical/config_utils.py
stratovolquant/web_app/__init__.py
stratovolquant/web_app/app.py
stratovolquant/web_app/config.py
stratovolquant/web_app/server.py
stratovolquant/web_app/users_mgt.py
stratovolquant/web_app/views/__init__.py
stratovolquant/web_app/views/login.py
stratovolquant/web_app/views/login_fd.py
stratovolquant/web_app/views/logout.py
stratovolquant/web_app/views/success.py
stratovolquant-0.0.14.dist-info/LICENSE.txt
stratovolquant-0.0.14.dist-info/METADATA
stratovolquant-0.0.14.dist-info/WHEEL
stratovolquant-0.0.14.dist-info/top_level.txt
stratovolquant-0.0.14.dist-info/RECORD
